LICENSE.md
MANIFEST.in
README
pyproject.toml
setup.py
tenns_modules/__init__.py
tenns_modules/version.py
tenns_modules.egg-info/PKG-INFO
tenns_modules.egg-info/SOURCES.txt
tenns_modules.egg-info/dependency_links.txt
tenns_modules.egg-info/requires.txt
tenns_modules.egg-info/top_level.txt
tenns_modules/export/__init__.py
tenns_modules/export/onnx_export.py
tenns_modules/modules/__init__.py
tenns_modules/modules/spatiotemporal_block.py