Metadata-Version: 2.4
Name: tenns_modules
Version: 0.3.0
Summary: TENNs modules definition.
Author: Brainchip
Maintainer-email: Kevin Tsiknos <ktsiknos@brainchip.com>
License: LICENSE.md
Project-URL: Documentation, https://doc.brainchipinc.com
Requires-Python: >=3.10
License-File: LICENSE.md
Requires-Dist: torch>=2.6
Requires-Dist: scipy
Requires-Dist: numpy
Requires-Dist: onnxscript~=0.4.0
Requires-Dist: setuptools
Requires-Dist: setuptools_scm
Provides-Extra: test
Requires-Dist: pytest; extra == "test"
Requires-Dist: cnn2snn>=2.17.0; extra == "test"
Dynamic: license-file
